{
  "description": "光遇工具箱 - Sky Toolbox",
  "packOptions": {
    "ignore": [],
    "include": []
  },
  "setting": {
    "urlCheck": false,
    "es6": true,
    "enhance": true,
    "postcss": true,
    "preloadBackgroundData": false,
    "minified": true,
    "newFeature": false,
    "coverView": true,
    "nodeModules": false,
    "autoAudits": false,
    "showShadowRootInWxmlPanel": true,
    "scopeDataCheck": false,
    "uglifyFileName": false,
    "checkInvalidKey": true,
    "checkSiteMap": true,
    "uploadWithSourceMap": true,
    "compileHotReLoad": false,
    "lazyloadPlaceholderEnable": false,
    "useMultiFrameRuntime": true,
    "useApiHook": true,
    "useApiHostProcess": true,
    "babelSetting": {
      "ignore": [],
      "disablePlugins": [],
      "outputPath": ""
    },
    "condition": false,
    "compileWorklet": false,
    "packNpmManually": false,
    "packNpmRelationList": [],
    "minifyWXSS": true,
    "minifyWXML": true,
    "localPlugins": false,
    "disableUseStrict": false,
    "useCompilerPlugins": false,
    "swc": false,
    "disableSWC": true
  },
  "compileType": "miniprogram",
  "cloudfunctionRoot": "cloudfunctions/",
  "libVersion": "3.16.1",
  "appid": "wx845f61de0b326b75",
  "projectname": "sky-toolbox",
  "condition": {},
  "simulatorPluginLibVersion": {},
  "editorSetting": {},
  "cloudfunctionTemplateRoot": "cloudfunctionTemplate/"
}